{
  "type": "Feature",
  "properties": {
    "iso:country":"CN",
    "sg:address":"No. 7, Fengxian M. Rd., Haidian District",
    "sg:city":"Beijing",
    "sg:classifiers":[
        {
            "category":"Professional",
            "subcategory":"Research",
            "type":"Services"
        }
    ],
    "sg:postcode":"100094",
    "sg:website":"http://www.chemclin.com",
    "wof:name":"Chemclin",
    "wof:placetype":"venue"
},
  "geometry": {"coordinates":[116.2475611,40.081069],"type":"Point"}
}