{
  "type": "Feature",
  "properties": {
    "iso:country":"CN",
    "sg:address":"21204 498 guo shoujing road",
    "sg:city":"Shanghai",
    "sg:classifiers":[
        {
            "category":"Professional",
            "subcategory":"Computer Services",
            "type":"Services"
        }
    ],
    "sg:postcode":"201203",
    "sg:tags":[
        "panorama",
        "virtual",
        "tour",
        "panoramic",
        "360",
        "spherical",
        "stitch",
        "reality",
        "vr",
        "realtor"
    ],
    "sg:website":"http://www.easypano.com",
    "wof:name":"Easypano",
    "wof:placetype":"venue"
},
  "geometry": {"coordinates":[114.169241,22.313675],"type":"Point"}
}